{"ext":{"1_e2pe4":{"path":"src/Core/Nodes/Vfx/NMirrorVfx.cs","type":"Script"},"2_imu0m":{"path":"images/events/mirror_mask3.png","texture":{"height":1024,"source":"images/events/mirror_mask3.png","src":"/images/sts2/event-vfx/runtime/images/events/mirror_mask3.webp","width":971},"type":"Texture2D"},"3_mnivr":{"path":"shaders/vfx/screencap.tres","type":"Shader"}},"nodes":[{"name":"MirrorVfx","parent":null,"props":{"anchor_bottom":1.0,"anchor_right":1.0,"anchors_preset":15,"grow_horizontal":2,"grow_vertical":2,"layout_mode":3,"script":{"$":"ExtResource","v":["1_e2pe4"]}},"type":"Control"},{"name":"Mask1","parent":".","props":{"clip_children":1,"position":{"$":"Vector2","v":[480,540]},"region_filter_clip_enabled":true,"texture":{"$":"ExtResource","v":["2_imu0m"]}},"type":"Sprite2D"},{"name":"Reflection","parent":"Mask1","props":{"anchor_bottom":0.5,"anchor_left":0.5,"anchor_right":0.5,"anchor_top":0.5,"anchors_preset":8,"grow_horizontal":2,"grow_vertical":2,"material":{"$":"SubResource","v":["ShaderMaterial_ece8p"]},"metadata/_edit_use_anchors_":true,"offset_left":-1040.0,"offset_right":880.0,"offset_top":-1080.0,"pivot_offset":{"$":"Vector2","v":[960,540]}},"type":"ColorRect"},{"name":"Mask2","parent":".","props":{"clip_children":1,"position":{"$":"Vector2","v":[480,540]},"region_filter_clip_enabled":true,"texture":{"$":"ExtResource","v":["2_imu0m"]}},"type":"Sprite2D"},{"name":"Reflection","parent":"Mask2","props":{"anchor_bottom":0.5,"anchor_left":0.5,"anchor_right":0.5,"anchor_top":0.5,"anchors_preset":8,"grow_horizontal":2,"grow_vertical":2,"material":{"$":"SubResource","v":["ShaderMaterial_ece8p"]},"metadata/_edit_use_anchors_":true,"offset_left":-1040.0,"offset_right":880.0,"offset_top":-1080.0,"pivot_offset":{"$":"Vector2","v":[960,540]},"rotation":-0.0349066},"type":"ColorRect"},{"name":"Mask3","parent":".","props":{"clip_children":1,"position":{"$":"Vector2","v":[480,540]},"region_filter_clip_enabled":true,"texture":{"$":"ExtResource","v":["2_imu0m"]}},"type":"Sprite2D"},{"name":"Reflection","parent":"Mask3","props":{"anchor_bottom":0.5,"anchor_left":0.5,"anchor_right":0.5,"anchor_top":0.5,"anchors_preset":8,"grow_horizontal":2,"grow_vertical":2,"material":{"$":"SubResource","v":["ShaderMaterial_ece8p"]},"metadata/_edit_use_anchors_":true,"offset_left":-1040.0,"offset_right":880.0,"offset_top":-1080.0,"pivot_offset":{"$":"Vector2","v":[960,540]},"rotation":0.0349066},"type":"ColorRect"}],"resources":{"ShaderMaterial_ece8p":{"props":{"shader":{"$":"ExtResource","v":["3_mnivr"]}},"type":"ShaderMaterial"}},"source":"scenes/vfx/whole_screen/mirror_vfx.tscn","version":1}
